collective.volto.gdprcookie-1.0.4-py3.11-nspkg.pth
collective/volto/gdprcookie/__init__.py
collective/volto/gdprcookie/config.py
collective/volto/gdprcookie/configure.zcml
collective/volto/gdprcookie/interfaces.py
collective/volto/gdprcookie/permissions.zcml
collective/volto/gdprcookie/setuphandlers.py
collective/volto/gdprcookie/testing.py
collective/volto/gdprcookie/browser/__init__.py
collective/volto/gdprcookie/browser/configure.zcml
collective/volto/gdprcookie/browser/controlpanel.py
collective/volto/gdprcookie/locales/README.rst
collective/volto/gdprcookie/locales/__init__.py
collective/volto/gdprcookie/locales/collective.volto.gdprcookie.pot
collective/volto/gdprcookie/locales/update.py
collective/volto/gdprcookie/locales/update.sh
collective/volto/gdprcookie/locales/en/LC_MESSAGES/collective.volto.gdprcookie.po
collective/volto/gdprcookie/locales/it/LC_MESSAGES/collective.volto.gdprcookie.po
collective/volto/gdprcookie/profiles/default/browserlayer.xml
collective/volto/gdprcookie/profiles/default/catalog.xml
collective/volto/gdprcookie/profiles/default/controlpanel.xml
collective/volto/gdprcookie/profiles/default/metadata.xml
collective/volto/gdprcookie/profiles/default/rolemap.xml
collective/volto/gdprcookie/profiles/default/registry/main.xml
collective/volto/gdprcookie/profiles/uninstall/browserlayer.xml
collective/volto/gdprcookie/restapi/__init__.py
collective/volto/gdprcookie/restapi/configure.zcml
collective/volto/gdprcookie/restapi/controlpanel.py
collective/volto/gdprcookie/restapi/deserializer.py
collective/volto/gdprcookie/restapi/get.py
collective/volto/gdprcookie/restapi/serializer.py
collective/volto/gdprcookie/tests/__init__.py
collective/volto/gdprcookie/tests/test_controlpanel_api.py
collective/volto/gdprcookie/tests/test_expander.py
collective/volto/gdprcookie/tests/test_get_gdpr_settings.py
collective.volto.gdprcookie-1.0.4.dist-info/LICENSE.GPL
collective.volto.gdprcookie-1.0.4.dist-info/LICENSE.rst
collective.volto.gdprcookie-1.0.4.dist-info/METADATA
collective.volto.gdprcookie-1.0.4.dist-info/WHEEL
collective.volto.gdprcookie-1.0.4.dist-info/entry_points.txt
collective.volto.gdprcookie-1.0.4.dist-info/namespace_packages.txt
collective.volto.gdprcookie-1.0.4.dist-info/top_level.txt
collective.volto.gdprcookie-1.0.4.dist-info/RECORD
